pod_billing/__init__.py
pod_billing/consts.py
pod_billing/json_schema.json
pod_billing/json_schema_direct_withdraw.json
pod_billing/json_schema_settlement.json
pod_billing/json_schema_voucher.json
pod_billing/pod_billing.py
pod_billing/pod_direct_withdraw.py
pod_billing/pod_settlement.py
pod_billing/pod_voucher.py
pod_billing/services.json
pod_billing/services_direct_withdraw.json
pod_billing/services_settlement.json
pod_billing/services_voucher.json
pod_billing/version.py
pod_billing-1.2.0.dist-info/METADATA
pod_billing-1.2.0.dist-info/WHEEL
pod_billing-1.2.0.dist-info/top_level.txt
pod_billing-1.2.0.dist-info/RECORD
