Metadata-Version: 2.1
Name: pod-billing
Version: 1.2.0
Summary: POD Billing services
Home-page: https://github.com/FanapSoft/pod-billing-python-sdk
Author: ReZa ZaRe
Author-email: rz.zare@gmail.com
License: MIT
Project-URL: Source, https://github.com/FanapSoft/pod-billing-python-sdk
Project-URL: Documentation, http://docs.pod.ir/v1.0.0.2/PODSDKs/python/5300/billing
Project-URL: Tracker, https://github.com/FanapSoft/pod-billing-python-sdk/issues
Keywords: POD,billing,invoice,issue invoice,settlement,voucher,discount,pod sdk
Platform: UNKNOWN
Classifier: Natural Language :: Persian
Classifier: Natural Language :: English
Classifier: Programming Language :: Python
Classifier: Programming Language :: Python :: 2
Classifier: Programming Language :: Python :: 2.7
Classifier: Programming Language :: Python :: 3
Classifier: Programming Language :: Python :: 3.5
Classifier: Programming Language :: Python :: 3.6
Classifier: Programming Language :: Python :: 3.7
Requires-Python: >=2.7
Requires-Dist: pod-base (<2,>=1.0.3)
Requires-Dist: pod-export (<2,>=1.0.1)
Requires-Dist: pod-common (<2,>=1.0.2)
